odoo/addons/account_asset_batch_compute/README.rst
odoo/addons/account_asset_batch_compute/__init__.py
odoo/addons/account_asset_batch_compute/__manifest__.py
odoo/addons/account_asset_batch_compute/data/queue_data.xml
odoo/addons/account_asset_batch_compute/i18n/account_asset_batch_compute.pot
odoo/addons/account_asset_batch_compute/i18n/fr.po
odoo/addons/account_asset_batch_compute/models/__init__.py
odoo/addons/account_asset_batch_compute/models/account_asset.py
odoo/addons/account_asset_batch_compute/readme/CONTRIBUTORS.rst
odoo/addons/account_asset_batch_compute/readme/DESCRIPTION.rst
odoo/addons/account_asset_batch_compute/static/description/icon.svg
odoo/addons/account_asset_batch_compute/static/description/index.html
odoo/addons/account_asset_batch_compute/tests/__init__.py
odoo/addons/account_asset_batch_compute/tests/test_account_asset_batch_compute.py
odoo/addons/account_asset_batch_compute/wizards/__init__.py
odoo/addons/account_asset_batch_compute/wizards/account_asset_compute.py
odoo/addons/account_asset_batch_compute/wizards/account_asset_compute_views.xml
odoo13_addon_account_asset_batch_compute-13.0.1.0.1.dev5.dist-info/METADATA
odoo13_addon_account_asset_batch_compute-13.0.1.0.1.dev5.dist-info/WHEEL
odoo13_addon_account_asset_batch_compute-13.0.1.0.1.dev5.dist-info/top_level.txt
odoo13_addon_account_asset_batch_compute-13.0.1.0.1.dev5.dist-info/RECORD
