Metadata-Version: 2.1
Name: odoo13-addon-account-asset-batch-compute
Version: 13.0.1.0.1.dev5
Summary: Add the possibility to compute assets in batch
Home-page: https://github.com/OCA/account-financial-tools
Author: ACSONE SA/NV,ForgeFlow,Odoo Community Association (OCA)
Author-email: support@odoo-community.org
License: AGPL-3
Platform: UNKNOWN
Classifier: Programming Language :: Python
Classifier: Framework :: Odoo
Classifier: Framework :: Odoo :: 13.0
Classifier: License :: OSI Approved :: GNU Affero General Public License v3
Requires-Python: >=3.5
Requires-Dist: odoo13-addon-account-asset-management
Requires-Dist: odoo13-addon-queue-job
Requires-Dist: odoo <13.1dev,>=13.0a
